doris_mcp-0.2.0.dist-info/licenses/LICENSE.txt
doris_mcp_server/__init__.py
doris_mcp_server/config.py
doris_mcp_server/main.py
doris_mcp_server/mcp_core.py
doris_mcp_server/sse_server.py
doris_mcp_server/streamable_server.py
doris_mcp-0.2.0.dist-info/METADATA
doris_mcp-0.2.0.dist-info/WHEEL
doris_mcp-0.2.0.dist-info/entry_points.txt
doris_mcp-0.2.0.dist-info/top_level.txt
doris_mcp-0.2.0.dist-info/RECORD
