Metadata-Version: 2.4
Name: doris-mcp
Version: 0.2.0
Summary: Doris MCP Server for Cursor integration
Author: Doris MCP Team - Yijia Su
License-Expression: Apache-2.0
Requires-Python: >=3.12
License-File: LICENSE.txt
Requires-Dist: mcp[cli]>=1.0.0
Requires-Dist: pymysql>=1.0.2
Requires-Dist: pandas>=1.5.0
Requires-Dist: numpy>=1.20.0
Requires-Dist: scikit-learn>=1.0.0
Requires-Dist: python-dotenv>=0.19.0
Requires-Dist: pydantic>=1.10.0
Requires-Dist: requests>=2.28.0
Requires-Dist: openai>=1.66.3
Requires-Dist: fastapi>=0.95.0
Requires-Dist: uvicorn>=0.21.0
Requires-Dist: simplejson>=3.17.0
Provides-Extra: dev
Requires-Dist: pytest>=7.0.0; extra == "dev"
Requires-Dist: black>=23.0.0; extra == "dev"
Requires-Dist: isort>=5.12.0; extra == "dev"
Dynamic: license-file
